pyweatherfr/__init__.py
pyweatherfr/app.py
pyweatherfr/args.py
pyweatherfr/log.py
pyweatherfr/meteofrance.py
pyweatherfr/openstreetmap.py
pyweatherfr/update.py
pyweatherfr-5.4.0.dist-info/LICENSE.txt
pyweatherfr-5.4.0.dist-info/METADATA
pyweatherfr-5.4.0.dist-info/WHEEL
pyweatherfr-5.4.0.dist-info/entry_points.txt
pyweatherfr-5.4.0.dist-info/top_level.txt
pyweatherfr-5.4.0.dist-info/RECORD
